netx_hboot_image_compiler/__init__.py
netx_hboot_image_compiler/__main__.py
netx_hboot_image_compiler/elf_support.py
netx_hboot_image_compiler/hboot_image.py
netx_hboot_image_compiler/hboot_netx4000_patch_table.xml
netx_hboot_image_compiler/hboot_netx4000_relaxed_patch_table.xml
netx_hboot_image_compiler/hboot_netx56_patch_table.xml
netx_hboot_image_compiler/hboot_netx90_mpw_patch_table.xml
netx_hboot_image_compiler/hboot_netx90_patch_table.xml
netx_hboot_image_compiler/hboot_netx90b_patch_table.xml
netx_hboot_image_compiler/netx90_app_iflash_image.py
netx_hboot_image_compiler/netx90_app_image.py
netx_hboot_image_compiler/option_compiler.py
netx_hboot_image_compiler/patch_definitions.py
netx_hboot_image_compiler/snippet_library.py
netx_hboot_image_compiler/top_hboot_image_hwc.xml
netx_hboot_image_compiler/top_hboot_image_mwc.xml
netx_hboot_image_compiler/hwconfig/__init__.py
netx_hboot_image_compiler/hwconfig/__main__.py
netx_hboot_image_compiler/hwconfig/hboot_config.xml
netx_hboot_image_compiler/hwconfig/hwconfig.py
netx_hboot_image_compiler/hwconfig/hwconfig_version.py
netx_hboot_image_compiler/hwconfig/netx90.xml
netx_hboot_image_compiler/hwconfig/netx90_rev0_peripherals.xml
netx_hboot_image_compiler/hwconfig/netx90_rev1_peripherals.xml
netx_hboot_image_compiler/hwconfig/nrp_h90-re_fxdx.xml
netx_hboot_image_compiler-3.0.19.dist-info/LICENSE
netx_hboot_image_compiler-3.0.19.dist-info/METADATA
netx_hboot_image_compiler-3.0.19.dist-info/WHEEL
netx_hboot_image_compiler-3.0.19.dist-info/top_level.txt
netx_hboot_image_compiler-3.0.19.dist-info/RECORD
