Metadata-Version: 2.1
Name: netx-hboot-image-compiler
Version: 3.0.19
Summary: Image compiler for Hilscher netX90 Second-Stage Bootloader
Home-page: https://github.com/pfox89/netx_hboot_image_compiler.git
Author: Paul Fox
Author-email: paul.fox@temposonics.com
License: UNKNOWN
Platform: UNKNOWN
Classifier: Programming Language :: Python :: 3.7
Classifier: Operating System :: OS Independent
Classifier: Topic :: Software Development :: Embedded Systems
Classifier: License :: OSI Approved :: GNU General Public License v2 (GPLv2)
Requires-Python: >=3.7
License-File: LICENSE
